Metadata-Version: 1.0
Name: LiveCricketScore
Version: 1.0
Summary: It will give you a notification in windows 10 with the live cricket score
Home-page: https://github.com/manavrawat10/LiveScoreNotification
Author: Manvenddra Rawat
Author-email: manvenddra.rawat@gmail.com
License: Manvenddra
Platform: UNKNOWN
